{
  "title": "A registration form",
  "description": "A simple form example.",
  "type": "object",
  "required": [
    "firstName",
    "lastName"
  ],
  "properties": {
    "firstName": {
      "type": "string",
      "title": "First name"
    },
    "lastName": {
      "type": "string",
      "title": "Last name"
    },
    "age": {
      "type": "integer",
      "title": "Age"
    },
    "upload": {
      "type": "upload",
      "title": "Please upload your file"
    },
    "creatableSelectTest": {
      "type": "string",
      "title": "Example creatable select",
      "enum": ["test", "teete", "etetet"]
    },
    "select": {
      "type": "string",
      "title": "Example select",
      "enum": ["Yes", "No"]
    },
    "selectTest": {
      "type": "string",
      "title": "Example Multi Select",
      "enum": ["Yes", "No"]
    },
    "bio": {
      "type": "string",
      "title": "Bio"
    },
    "date": {
      "type": "material-date",
      "title": "Date"
    },
    "password": {
      "type": "string",
      "title": "Password",
      "minLength": 3
    },
    "telephone": {
      "type": "string",
      "title": "Telephone",
      "minLength": 10
    }
  }
}
